Workbook

Sheet OTC Data Elements
A1: OTC Data Model — Key Data Elements for Workshop Discussion
A2: Purpose: Facilitate alignment on core data definitions, business rules, and thresholds across Divisions
A3: OTC Stage | B3: Data Element | C3: Definition & Description | D3: Key Attributes | E3: Business Rules & Thresholds (For Discussion) | F3: Current System(s) of Record | G3: Known Issues & Gaps
A4: 1. Order Capture | B4: Customer / Client | C4: The legal entity or organisation purchasing services from an Inizio division. Represents the billable party and the top-level commercial relationship. | D4: Customer ID, Legal Name, Trading Name, Parent Account, Bill-to Address, Ship-to Address, Tax ID, Payment Terms, Credit Limit, Industry, Territory | E4: What is the minimum engagement value to create a formal customer record (e.g. >$10k)? Should a single global customer ID span all divisions? Who owns the parent-child hierarchy — and in which system? What naming convention applies across entities (e.g. "the ever-changing Inizio entity names")? | F4: HubSpot (prospect/pipeline) Certinia (Ignite) Maconomy (Evoke/Engage) Oracle Fusion (GL/AP/AR) Oracle EPM (planning) | G4: No single source of truth — each system maintains its own master data independently. Parent-child hierarchies inconsistent across HubSpot, Certinia, and Oracle. Entity naming conventions change over time. No clear data steward or governance process.
B5: Account Hierarchy | C5: The parent-child structure linking related legal entities, subsidiaries, and trading entities under a single client umbrella. | D5: Grandparent Account, Parent Account, Child Account, Relationship Type, Hierarchy Level, Effective Date | E5: How many levels of hierarchy are needed (2? 3?)? Who is the data owner for cross-system hierarchy maintenance? How should acquisitions/name changes be handled — retroactively or point-forward? | F5: HubSpot, Certinia, Oracle Fusion (each maintains own version) | G5: "Not really clear who owns that hierarchy." Hierarchies in HubSpot do not always match Certinia or Oracle. No automated sync of hierarchy changes across systems.
B6: Opportunity / Deal | C6: A qualified sales opportunity representing potential revenue. Tracked through deal stages from prospect to closed-won. | D6: Opportunity ID, Deal Name, Stage, Probability, Expected Value, Expected Close Date, Division, Service Line, Owner, Associated Customer | E6: What is the minimum deal size to track in HubSpot (e.g. >$10k? >$25k?)? At what stage does an opportunity become a firm forecast inclusion? Should renewals and extensions be tracked as new opportunities or amendments? | F6: HubSpot (all divisions) Certinia (Ignite — dual sync) Maconomy (Evoke — no HubSpot integration) | G6: Vynamic logs opportunities in both HubSpot and Certinia (dual sync). HubSpot-to-Maconomy integration does not exist for Evoke. Deal structure in Vynamic differs from Putnam. Renewals process not consistently captured.
B7: Contract / MSA | C7: The Master Services Agreement — the overarching legal framework governing the commercial relationship with a client. Defines standard terms, liability, IP, and confidentiality. | D7: Contract ID, Client, Effective Date, Expiry Date, Auto-Renewal Flag, Standard/Non-Standard Terms, Signed Copy Location, Contract Status | E7: What is the threshold for requiring a formal MSA vs. a simplified letter agreement (e.g. >$50k annual value?)? What constitutes a "material amendment" requiring re-approval? Maximum contract term before mandatory review? | F7: HighQ (some divisions) Certinia (Ignite) Teams/Network Drives (ad hoc) No CLM system in place | G7: Contracts stored offline across multiple locations — no single repository. No e-signature (DocuSign) workflow. No CLM for version control, renewal tracking, or obligation management. Storage varies by division.
B8: Statement of Work (SOW) | C8: A project-level agreement under an MSA that defines scope, deliverables, pricing, timeline, and resourcing for a specific engagement. | D8: SOW ID, Associated MSA, Scope Description, Fee Type (Fixed/T&M/Hybrid), Total Value, Start Date, End Date, Billing Milestones, Rate Card Reference, PO Requirement Flag | E8: What is the minimum SOW value that justifies full project setup (e.g. >$10k?)? Should micro-engagements (<$5k) follow a simplified process? How should scope changes/amendments be numbered and tracked? What % variance from original SOW triggers re-approval? | F8: Created manually (Word/PDF) Stored in Certinia / Maconomy / HighQ / Teams drives HubSpot captures summary fields | G8: SOW creation is entirely manual — no template library or AI extraction. Pricing models frequently built in Excel then entered separately into HubSpot and Certinia. No automated SOW-to-project setup.
B9: Purchase Order (PO) | C9: The client's formal authorisation to bill against a SOW. Required by many clients before invoicing can begin. | D9: PO Number, Client, SOW Reference, PO Value, Currency, Validity Period, PO Line Items, Remaining Balance, Status | E9: Oracle currently supports only one PO per contract — is this the target state or does multi-PO need to be enabled? What is the tolerance for PO value vs. SOW value mismatch (e.g. within 5%)? How should PO renewals/extensions be handled? What triggers a PO balance alert (e.g. 80% consumed)? | F9: Oracle Fusion (AR) Certinia (Ignite) Maconomy (Evoke/Engage) | G9: Oracle only holds one PO per contract — workaround "Part 2" contracts split financial records. POs arrive via email, portals, or direct contact with no unified intake. No automated PO-to-SOW matching.
A10: 2. Demand & Supply Planning | B10: Revenue Forecast | C10: The projected revenue for a defined period, combining contracted backlog, weighted pipeline, and expected renewals. | D10: Forecast Period, Division, Entity, Contracted Revenue, Weighted Pipeline, Expected Renewals, Forecast Confidence, Variance to Prior, Forecast Owner | E10: What is the forecast cadence — monthly, quarterly, rolling 12-month? At what pipeline probability should deals enter the forecast (e.g. >50%? >75%?)? How should intercompany/cross-entity revenue be counted — at source or destination? What variance threshold triggers an escalation review? | F10: Oracle EPM (target) Certinia (Ignite — partial) Excel / Power BI (all divisions) | G10: EPM not used for scenario planning despite being available. System timeouts and freezes drive users to Excel. Forecasting managed entirely in Excel for Evoke and Engage. No link between Workday and forecast for true project profitability.
B11: Resource / Staff Assignment | C11: The allocation of named individuals (FTEs, contractors, freelancers) to specific projects, including role, utilisation %, and time period. | D11: Employee ID, Name, Role, Division, Project Assignment, Allocation %, Start Date, End Date, Cost Rate, Bill Rate, Employee Type (FTE/Contractor) | E11: What is the minimum allocation % that counts as "assigned" (e.g. >10%)? How far ahead should resource plans extend (e.g. 90 days? 6 months?)? What utilisation target defines "fully staffed"? How are freelancer-to-FTE conversions handled in the system? | F11: Certinia PSA (Ignite) Maconomy (Evoke/Engage) Workday (HR source) Excel (workforce planning) | G11: Workday does not sync with Maconomy — name, title, LOA, employee type changes require manual updates. No PSA-based resource matching in Evoke/Engage. Ignite auto-loads from Workday; others are manual.
A12: 3. Service Delivery | B12: Project | C12: The operational delivery unit — a structured container for tracking time, costs, budgets, milestones, and revenue against a SOW. | D12: Project ID, Project Name, Client, SOW Reference, Project Manager, Status, Start Date, End Date, Fee Type, Budget, Division, Entity | E12: Should every SOW create exactly one project, or can a SOW span multiple sub-projects? What is the maximum project duration before mandatory review? When should a project be marked "Closed" — final deliverable or final payment? What is the definition of an "active" project for reporting? | F12: Certinia (Ignite — Putnam/Vynamic/RP/STEM) Maconomy (Evoke/Engage) Oracle PPM (Medical) | G12: Certinia configured differently across Ignite entities — "three, maybe three sets of configurations." 800+ unique project templates in Oracle (Medical). No automated SOW-to-project creation. RP going live April, STEM not yet aligned.
B13: Budget | C13: The financial plan for a project, defining expected revenue, costs, and margin. May include contract budget (client-signed value) and working budget (internal delivery estimate). | D13: Budget ID, Project, Contract Budget, Working Budget, Budget Type (Fixed/T&M), Labour Cost, Other Cost, Passthrough, Margin %, Budget Status, Approval Date | E13: What variance between contract budget and working budget is acceptable (e.g. within 10%)? At what % budget consumed should alerts trigger (e.g. 75%, 90%)? How should budget increases be approved — same authority as original or escalated? Should passthrough costs be included in budget or tracked separately? | F13: Certinia (Ignite) Maconomy (Evoke/Engage) Oracle PPM (Medical) Excel (all — supplementary) | G13: Maconomy requires dual budget entry ("contract budget" and "working budget"). Pricing models built in Excel then entered separately. EPM loaded manually even though data exists in Workday/Certinia. Frequent budget changes within SOWs (Evoke).
B14: Timesheet / Timecard | C14: A record of hours worked by an individual against a specific project, task, and date. The primary input for T&M billing and utilisation reporting. | D14: Timecard ID, Employee, Project, Task, Date, Hours, Billable Flag, Approval Status, Submitted Date, Approved By | E14: What is the submission deadline (e.g. every Friday by 5pm?)? What is the maximum retrospective correction period (e.g. current month only?)? What threshold of missing timesheets triggers automated escalation? Should non-billable time categories be standardised across divisions? | F14: Certinia (Ignite) Maconomy (Evoke/Engage) Oracle PPM (Medical — UK only) Excel (Medical — other geos) | G14: RevOps spends significant time chasing and reviewing submissions. Users cannot self-correct in some systems — must raise tickets (Maconomy) or email finance. Medical uses different systems by geography. No standardised non-billable categories.
B15: Expense | C15: Out-of-pocket costs incurred by staff and charged to a project (travel, accommodation, materials, etc.). | D15: Expense ID, Employee, Project, Category, Amount, Currency, Date, Receipt Flag, Billable/Non-Billable, Client Reimbursable, Approval Status | E15: What expense categories are billable to clients vs. absorbed internally? What is the per-item approval threshold (e.g. >$500 requires manager sign-off?)? What is the maximum claim period (e.g. within 60 days of incurrence?)? Should passthrough expenses follow a different approval path? | F15: Concur (most divisions) Certinia expense module (Ignite) Oracle (Medical) | G15: Concur used but not integrated cleanly across all divisions. Ignite uses Certinia expense reports, not Concur. Varying expense systems across divisions AND geographies.
B16: Milestone | C16: A defined deliverable or progress marker within a project that may trigger billing, revenue recognition, or client approval. | D16: Milestone ID, Project, Description, Type (Billing/Revenue/Delivery), Target Date, Actual Date, Value, Status, Client Acceptance Required, Approved By | E16: Should billing milestones and revenue milestones be treated as the same or separate entities? What evidence constitutes "client acceptance" — email, portal sign-off, formal letter? What is the tolerance for milestone date slippage before escalation? Can milestones be partially completed? | F16: Certinia (Ignite — partial) Maconomy (Evoke/Engage — manual) Oracle PPM (Medical — no milestones) | G16: Medical sends milestone progress via Excel to finance for upload. Certinia not configured to support revenue recognition on milestones for all entities. No automated milestone triggers. Finance manually marks milestones and validates revenue readiness.
A17: 4. Revenue Recognition | B17: Revenue Event | C17: A transaction that records earned revenue against a project, applying the appropriate recognition method (over time, point in time, percentage of completion). | D17: Revenue Event ID, Project, Period, Recognition Method, Gross Amount, Adjustment Amount, Net Amount, Status, Journal Reference, Approval Status | E17: Which recognition method applies by fee type — T&M (as delivered), Fixed Fee (POC or milestone), Hybrid? What is the minimum revenue event threshold to avoid micro-postings (e.g. >$100?)? What constitutes a "material" revenue adjustment requiring senior approval? How should intercompany revenue be recognised — at contract or delivery entity level? | F17: Certinia (Ignite — partially automated) Maconomy (Evoke/Engage — manual) Oracle (Medical — manual POC files) | G17: Revenue recognition requires manual intervention across all divisions. Certinia not configured for milestone-based rev rec in all Ignite entities. Lack of reasonableness checks (Evoke). Medical uses manual POC files. Approaches vary: billing milestones vs. revenue milestones vs. time-based.
B18: Accrued / Deferred Revenue | C18: Revenue recognised but not yet billed (accrued) or billed but not yet earned (deferred). Critical for accurate financial reporting. | D18: Project, Period, Accrued Amount, Deferred Amount, Ageing Bucket, Reason Code, Resolution Owner, Expected Resolution Date | E18: What ageing threshold triggers review of accrued revenue (e.g. >60 days unbilled?)? What deferred revenue balance requires escalation? How should OA (on account) / parent invoicing impact accrual treatment? What is the maximum period revenue can remain accrued before write-off review? | F18: Certinia (Ignite) Maconomy (Evoke/Engage) Oracle (Medical) | G18: Accrued and deferred revenue builds up due to OA invoicing or parent invoicing (Evoke). Revenue recognised at sub-project level but billings need offsetting. Passthrough cost and revenue not cleanly handled — Certinia set up before material passthrough volumes existed.
A19: 5. Invoicing & Billing | B19: Invoice | C19: A formal billing document issued to the client for services rendered, based on agreed milestones, time & materials, or fixed-fee schedules. | D19: Invoice Number, Client, Project, PO Reference, Invoice Date, Due Date, Currency, Line Items, Gross Amount, Tax, Net Amount, Status, Delivery Method | E19: What is the minimum invoice value to issue (e.g. >$500? >$1,000?)? What is the standard payment term by client tier (e.g. Net 30, Net 45, Net 60?)? Should draft invoices require business approval or only GFS quality review? What is the maximum number of line items per invoice before splitting? | F19: Certinia (Ignite) Maconomy (Evoke/Engage) Oracle AR (Medical) Client portals (Tungsten, Ariba, etc.) | G19: No automatic invoice generation in Evoke. Invoice creation still requires manual user action in Certinia. 50%+ portal-based submission for Engage. Invoicing is a mix of hours, supplier costs, milestones, and software utilisation. Manual portal entry for large volumes.
B20: Billing Plan / Schedule | C20: The planned invoicing schedule for a project, defining when and how much will be billed over the engagement lifecycle. | D20: Plan ID, Project, Billing Frequency, Milestone Schedule, Planned Amount per Period, Currency, Fee Type, PO Linkage, Status | E20: Should billing plans be mandatory for all projects or only above a threshold (e.g. >$25k?)? What is the standard billing frequency by fee type (T&M = monthly, Fixed = milestone?)? What tolerance for billing plan vs. actual invoicing variance before review? How should "billing on behalf" (intercompany) plans be structured? | F20: Certinia (Ignite) Maconomy (Evoke — invoicing plan module) Oracle (Medical) | G20: Maconomy invoicing plan module exists but if invoicing is not raised through it, amounts appear unbilled. Tickbox needed to flag manual invoicing. Different bill plan structures across divisions.
A21: 6. Collections | B21: Payment / Cash Receipt | C21: A payment received from a client against one or more outstanding invoices. Must be matched and applied to clear AR balances. | D21: Payment ID, Client, Amount, Currency, Payment Date, Payment Method, Bank Reference, Applied Invoice(s), Unapplied Amount, Status | E21: What is the auto-match tolerance for payment-to-invoice matching (e.g. within $1? within 1%?)? What is the target DSO (Days Sales Outstanding) by division? How should partial payments be allocated — oldest invoice first or pro-rata? What payment ageing triggers escalation to collections? | F21: Oracle Fusion (cash application) Certinia (payment feeds) Bank integrations | G21: Cash application happens in Oracle with feeds to Certinia. Hope Bot handles some automation but only operates Monday-Thursday. Treasury needs real-time cash receipting. GFS transition at different stages across divisions.
B22: AR Ageing / Dispute | C22: An outstanding receivable that is overdue or contested by the client, requiring investigation and resolution. | D22: Dispute ID, Invoice Reference, Client, Dispute Reason, Ageing Bucket (Current/30/60/90/120+), Amount, Owner, Status, Resolution Date, Credit Note Reference | E22: What ageing buckets should be reported (30/60/90/120+ days?)? At what ageing threshold does a dispute require senior finance involvement (e.g. >90 days?)? What is the write-off authority limit by role (e.g. <$5k = Finance Manager, >$5k = Finance Director?)? How should credit notes be linked to original invoices and POs? | F22: Oracle Fusion (AR) Excel (cash forecasting — all divisions) PFRM bolt-on (Medical) | G22: Split ownership between GFS and divisions for collections outreach. Cash forecasting entirely Excel-based. Client services unable to see payment status — "potentially due to licensing." Teams spend too much time identifying the right finance contact for cross-entity disputes.
A23: Cross-Cutting | B23: Intercompany Transaction | C23: A financial transaction between Inizio legal entities — e.g. when one entity delivers services under another entity's client contract. | D23: IC Transaction ID, Source Entity, Destination Entity, Project, Amount, Currency, Transfer Pricing Method, IC Invoice Reference, Elimination Status | E23: What transfer pricing method applies (cost-plus, market rate, pre-agreed %)? How should intercompany revenue vs. cost be recognised — simultaneously or with a lag? What is the maximum IC balance before mandatory netting/settlement? Should IC invoices follow the same approval workflow as external? | F23: Certinia (Ignite) Maconomy (Evoke/Engage) Oracle Fusion (consolidation) | G23: Certinia does not natively support all required multi-entity revenue scenarios. Teams spend too much time identifying which entity owns the contract. Accrued/deferred/intercompany balances not properly aligned across entities.
B24: Passthrough Cost / Revenue | C24: Third-party costs incurred on behalf of a client (e.g. media spend, vendor costs, travel) that are passed through at cost or with a markup. | D24: Passthrough ID, Project, Vendor, Cost Amount, Markup %, Client Billable Amount, Cost Category, Invoice Linkage, Status | E24: What is the standard passthrough markup % (0%? 5%? 10%?)? Should passthrough be included in project budget or tracked as a separate line? What approval threshold applies for passthrough commitments (e.g. >$10k?)? How should passthrough revenue be recognised — when incurred or when billed? | F24: Certinia (Ignite) Maconomy (Evoke/Engage) Oracle (Medical) | G24: Certinia was set up before material passthrough volumes existed — configuration gaps. Manual allocation of passthrough costs across projects. Treatment varies significantly by division.
A26: Note: Business rules & thresholds (amber column) are proposed starting points for workshop discussion — not final decisions. Known issues are drawn from WS1/WS2/WS3 workshop findings.

Sheet Process Design
A1: To-be OTC Process Design (DRAFT - FOR DISCUSSION) | V1: Addressed | W1: Open Question | X1: Noted - no change made at this time
U3: Please review and enter comments in your respective column | AA3: Dawn / Don
A4: x | B4: x | C4: x | D4: x | E4: x | F4: x | G4: x | Q4: x | R4: y | S4: y
A5: AI Agent? | B5: System / Tool | C5: Level (L1-L4) | D5: Step Number | E5: Step Name | F5: Step Description | G5: Step Type | H5: Automated? | I5: Key Differences / Call-outs from As-is (EVOKE) | J5: Key Differences / Call-outs from As-is (IGNITE) | K5: Key Differences / Call-outs from As-is (ENGAGE) | L5: Key Differences / Call-outs from As-is (MEDICAL) | M5: As-Is Owner (EVOKE) | N5: As-Is Owner (IGNITE) | O5: As-Is Owner (ENGAGE) | P5: As-Is Owner (MEDICAL) | Q5: To-be RACI – Responsible | R5: To-be RACI – Accountable | S5: To-be RACI – Contributing | U5: GFS Comments | V5: Evoke Comments | W5: Ignite Comments | X5: Engage Comments | Y5: Medical Comments | AA5: SOX / Audit Hotspots for Consideration | AC5: Changes from today | AD5: Artefacts
B6: System / Tool | C6: Level | D6: Seq # | E6: Step Name | F6: Description | G6: Shape Type | H6: Y/N/Partial | I6: Description | J6: Description | K6: Description | L6: Description | M6: As-Is Owner | N6: As-Is Owner | O6: As-Is Owner | P6: As-Is Owner | Q6: Responsible (R) | R6: Accountable (A) | S6: Contributing (C)
B7: CRM / CLM / PSA / ERP / Contract Capture Agent | C7: L1 | D7: 1 | E7: Order Capture | F7: Establish and govern customer, contractual, commercial and project setup requirements from initial opportunity creation through to project activation, billing readiness and operational delivery enablement | G7: Start | H7: Partial | Q7: Client Services / Account Managers | R7: Client Services / Account Managers
B8: CRM | C8: L2 | D8: 1.1 | E8: Customer & Contract Setup | F8: Establish the client relationship, execute contractual agreements, define commercial and billing framework terms, and complete operational setup requirements to support downstream delivery, revenue recognition and invoicing | G8: Process | H8: Partial | I8: All SOW's, Change Orders and PO's are stored in Maconomy. MSAs stored in HighQ, SOWs in Maconomy and finance folders. Contract creation is entirely manual. 70% of clients use SOW templates within MSA; 30% use internal templates. Move to centralise contracts in Ireland is underway but incomplete. | J8: Customer setup done in HubSpot by innovation & growth team (not div finance). Contract setup also in HubSpot by account managers. Dual sync between HubSpot and Certinia required. No CLM or e-signature tools in use; contracts stored across HubSpot, Certinia, and HighQ with no single source of truth. | K8: SOW and PO saved on client drives (not centralised). In EU, MSAs stored as PDFs on local network drives per country, in local languages. Contracts managed locally with no standard process. Project management gives Excel to Finance for Oracle PPM input. HubSpot doesn't work well for EU Engage's people-supply business model. | L8: MSAs created on Teams drive (central team, not on teams) s based on client briefs. Pricing negotiated via email (via platofrm or email). HubSpot for new opportunities, Oracle for renewals. No CLM (HighQinizio wide), no e-signature, no centralised contract repository. | M8: Ops. / Div. Finance | N8: Innovation & Growth team / Operations | O8: Ops. / Div. Finance | P8: Operations | Q8: Sales | R8: Sales | V8: MM: All SOW's, Change Orders and PO's are stored in Maconomy. If something is stored in a local folder, it would only be a copy. We will not recognize revenue against a project without a contract tying to the contract total, attached in Maconomy. [refer to 1.2.4.12]
B9: CRM | C9: L3 | D9: 1.1.1 | E9: Customer Initiation | F9: Initiate customer and opportunity setup process from Sales / Business Development pipeline activity and capture preliminary customer and opportunity information | G9: Process | H9: N | I9: New business captured in HubSpot; existing account work may be tracked in Excel sheets. No standardised initiation workflow across C&T and Comms divisions. | J9: Initiated in HubSpot by innovation & growth team. Vynamic uses Certinia; Putnam and others use HubSpot. Separate start points that converge at Project Activation. | K9: BD team inputs into HubSpot for pipeline. In EU, HubSpot covers new opportunities but may not capture individual statements of work - only the overall project. Business model (people supply) does not align well with HubSpot's structure. | L9: HubSpot used for new opportunities. Oracle system used for renewals. HubSpot holds uncommitted pipeline; Oracle PPM holds committed work. | M9: Client Services | N9: Client Services (Innovation & Growth) | O9: Client Services (BD team) | P9: Client Services | Q9: Sales | R9: Sales | V9: KM: For Comms, at the end of the month our EVP of Growth sends out a chart for all deals within Hubspot that are considered qualifed. The value on the report has an annulized value and the expected close date. This is added into the financial packs and into Oracle project submission. KV: We’re currently developing a report to come from HubSpot to feed into a Power BI dashboard for revenue forecasting.
B10: CRM | C10: L4 | D10: 1.1.1.1 | E10: Create Prospect & Customer Record in CRM | F10: Create prospect, company and associated contact records in CRM. Capture preliminary customer and opportunity details including client name, region, industry, service line and opportunity scope. Perform duplicate review and link to existing customer records where applicable | G10: Process | H10: N | I10: HubSpot used for growth/new business side. Engagement type and deal structure may differ between C&T and Comms. | J10: HubSpot used across Ignite but deal/service-line structures differ by entity (Putnam vs Vynamic). No standardised duplicate detection or merge process documented. | K10: HubSpot used for new pipeline but limited detail captured. EU Engage may not see individual SOWs in HubSpot, only overall project-level entries. | L10: HubSpot used for new opportunity capture but with limited structured data. Forecasts sit in HubSpot at pipeline level. | M10: Client Services | N10: Client Services (Innovation & Growth) | O10: Client Services (BD team) | P10: Client Services | Q10: Sales | R10: Sales
B11: CRM | C11: L4 | D11: 1.1.1.2 | E11: Opportunity Creation | F11: Create opportunity record in CRM and capture estimated value, engagement type, expected close date, pipeline stage, opportunity owner and preliminary commercial structure | G11: Process | H11: N | M11: Client Services | N11: Client Services (Innovation & Growth) | O11: Client Services (BD team) | P11: Client Services | Q11: Sales | R11: Sales
B12: Structured Excel / PSA / CRM | C12: L4 | D12: 1.1.1.3 | E12: Quote Generation | F12: Generate preliminary pricing estimate or quote based on expected scope, resource requirements, commercial model and applicable rate structure. Client Services leads quote development using approved commercial guardrails and standard cost rates maintained by Divisional Finance through annual tooling/rate card updates. Quote generation may be performed through PSA, CRM or structured pricing templates, as applicable. | G12: Process | H12: N | Q12: Client Services / Account Managers | R12: Sales | S12: Managing Director (MD) / Division Finance
B13: Structured Excel / PSA / CRM | C13: L4 | D13: 1.1.1.4 | E13: Margin Threshold Approval Required? | F13: Determine whether estimated engagement margin falls below defined approval threshold. Where threshold is breached, obtain approval from Divisional CFO and Pillar President prior to advancing opportunity | G13: Process | H13: N | Q13: Client Services / Account Managers | R13: Sales | S13: Division CFO / Division President
B14: CRM | C14: L4 | D14: 1.1.1.5 | E14: Pricing Governance Approval Required? | F14: Determine whether proposed pricing structure, discounting or commercial terms fall outside approved pricing guardrails or standard commercial thresholds. Where non-standard pricing or discounting applies, obtain approval through Pricing Council governance process prior to advancing opportunity | G14: Process | H14: N | Q14: Client Services / Account Managers | R14: Sales | S14: Pricing Council
B15: CRM | C15: L4 | D15: 1.1.1.6 | E15: Advance Opportunity Through Pipeline Stages | F15: Progress opportunity through defined CRM pipeline stages based on commercial qualification, proposal activity and client engagement status | G15: Process | H15: N | M15: Client Services | N15: Client Services (Innovation & Growth) | O15: Client Services (BD team) | P15: Client Services | Q15: Sales | R15: Sales
B16: CRM / ERP | C16: L4 | D16: 1.1.1.7 | E16: Existing Customer Record Check | F16: Determine whether customer already exists within ERP / master data systems and identify whether new customer setup or hierarchy updates are required | G16: Process | H16: N | I16: No automated trigger. Client data split across HubSpot, Maconomy, and Oracle. No integrated duplicate check between systems. | J16: No automated HubSpot-to-ERP check. Customer data exists across HubSpot, Certinia, and Oracle with fragmented parent/child hierarchies. Inconsistent naming and entity structures create duplicate maintenance risk. | K16: No automated check. Customer data split between HubSpot, Oracle Fusion, and Oracle PPM. EU countries manage customer records locally. | L16: No automated check between HubSpot and Oracle PPM. Templates created in Oracle for new products/clients but reuse is minimal (~800 templates in system). | M16: Client Services | N16: Client Services (Innovation & Growth) | O16: Client Services (BD team) | P16: Client Services | Q16: Client Services / Account Managers | R16: Client Services / Account Managers
B17: CRM / ServiceNow | C17: L4 | D17: 1.1.1.8 | E17: Customer Master Data Request Initiation | F17: Initiate customer master data setup request for new customers or required hierarchy/billing structure updates and route to Master Data Management team for review and processing | G17: Process | H17: N | I17: No automated ServiceNow workflow. Setup requests submitted manually. Two-form/two-system setup needed (Maconomy + Oracle) depending on division. | J17: No automated ServiceNow ticket creation. PO mailbox monitored by div finance (transitioning to GFS). Client reaches out directly or via Ariva portal. | K17: No automated request workflow. Project management gives Excel to Finance who manually input into Oracle PPM. EU countries manage setup locally. | L17: HubSpot connection to ServiceNow [to be confirmed] | M17: Operations | N17: Div. Finance (transitioning to GFS) | O17: Div. Finance | P17: Project Operations | Q17: Client Services / Account Managers | R17: Client Services / Account Managers
B18: ERP / ServiceNow | C18: L3 | D18: 1.1.2 | E18: Customer Master Data Creation | F18: Create customer master data record including customer hierarchy and required customer attributes to support downstream contracting, billing and reporting processes | G18: Process | H18: Partial | I18: Client setup may require activity in both Maconomy and Oracle. ServiceNow requests and manual setup steps needed. No unified customer hierarchy across systems. | J18: Client/account hierarchy fragmented across HubSpot, Certinia, Oracle Fusion, and Oracle EPM. Parent/child naming inconsistent. Current Certinia configurations vary across Ignite entities. | K18: Oracle PPM for cost side, Oracle Fusion for rest. Individual rates not captured in PPM - all managed outside in Excel. EU operations input project data manually from Excel handoffs. | L18: Oracle support team creates the record in Fusion. It is done manually using templates. Extent to which templates are re-used is minimal - ca. 800 templates are currently in the system Rates are the main driver of the proliferation | M18: Operations / Div. Finance | N18: GFS / Div. Finance | O18: Div. Finance | P18: GFS (Oracle Support) | Q18: Global Master Data | R18: Global Master Data | AC18: Disparat master data
B19: ServiceNow / ERP | C19: L4 | D19: 1.1.2.1 | E19: Customer Master Data Review | F19: Review customer master data submitted from CRM and identify missing, incomplete or conflicting customer attributes required for record creation. Populate missing fields where possible (e.g., internal segmentation codes) | G19: Process | H19: N | I19: No MDM workflow. Client data manually maintained across Maconomy and Oracle. Division-specific forms used for setup. | J19: No formal MDM ticket workflow. Data cleanup, export, upload, and reconciliation across systems is manual. Pricing models built in Excel then entered into HubSpot/Certinia. | K19: No MDM process. Finance manually enters client data into Oracle from project management Excel inputs. Rate data managed entirely outside PPM. | L19: Limited MDM. Teams have offline mapping tables on customer entities and drugs for reporting purposes | M19: Operations / Div. Finance | N19: GFS / Div. Finance | O19: Div. Finance | P19: GFS (Oracle Support) | Q19: Global Master Data | R19: Global Master Data
B20: ERP | C20: L4 | D20: 1.1.2.2 | E20: Client Services Input Required? | F20: Determine whether Client Services input is required to complete missing customer master data fields | G20: ="Decision If yes, proceed to step "&D21&" If no, proceed to "&D25&"" -> Decision If yes, proceed to step 1.1.2.3 If no, proceed to 1.1.3 | H20: N | M20: Operations / Div. Finance | N20: GFS / Div. Finance | O20: Div. Finance | P20: GFS (Oracle Support) | Q20: Global Master Data | R20: Global Master Data
B21: ServiceNow | C21: L4 | D21: 1.1.2.3 | E21: Request Additional Customer Information | F21: Request missing or incomplete customer information from Client Services or customer contacts where required for customer master setup | G21: Process | H21: Partial | M21: Operations / Div. Finance | N21: GFS / Div. Finance | O21: Div. Finance | P21: GFS (Oracle Support) | Q21: Global Master Data | R21: Global Master Data
B22: ServiceNow / Email | C22: L4 | D22: 1.1.2.4 | E22: Complete Customer Master Data | F22: Obtain and populate missing customer master data fields required for customer record creation, hierarchy setup and billing enablement | G22: Process | H22: N | M22: Client Services | N22: Client Services | O22: Client Services | P22: Client Services | Q22: Client Services / Account Managers | R22: Client Services / Account Managers | S22: Sales
B23: ERP | C23: L4 | D23: 1.1.2.5 | E23: Customer Record Creation | F23: Create customer record within ERP/MDM system and establish associated customer hierarchy, billing entity structure and customer identifiers | G23: Process | H23: N | M23: Operations / Div. Finance | N23: GFS | O23: Div. Finance | P23: GFS (Oracle Support) | Q23: Global Master Data | R23: Global Master Data
B24: ERP / CRM | C24: L4 | D24: 1.1.2.6 | E24: Customer ID & CRM Update | F24: Update CRM / customer source systems with created customer identifier and customer master record status | G24: Process | H24: Partial | M24: Operations / Div. Finance | N24: GFS | O24: Div. Finance | P24: GFS (Oracle Support) | Q24: Automated (or Global Master Data in absence of automation) | R24: Global Master Data
B25: Credit Platform / ERP | C25: L3 | D25: 1.1.3 | E25: Credit & Compliance Screening | F25: Perform customer credit assessment, financial due diligence and compliance screening to determine customer risk profile, payment terms, credit controls and onboarding eligibility | G25: Process | H25: Partial | I25: No formal credit screening process documented. Not a standard step in As-Is Evoke OTC process. | J25: No formal credit screening or risk scoring process documented in workshop notes. Credit assessment not described as a standard step in As-Is. | K25: No formal credit screening process documented. Not a standard step in As-Is Engage OTC process. | L25: No formal credit screening or compliance screening process documented in As-Is. | Q25: GFS - Credit | R25: GFS - Credit | U25: Nice to have (20, not 80). DJ Note: Could be part of the Sidetrade offering but again not an urgent Inizio need | AC25: Not performed today - no threshold (to be determined by the business)
B26: Third party provider assumed | C26: L4 | D26: 1.1.3.1 | E26: Compliance Screening | F26: Perform regulatory and policy screening checks including sanctions, AML, watchlists and restricted party validation to confirm the customer relationship is permissible prior to onboarding or credit approval | G26: Process | H26: N | Q26: GFS - Credit | R26: GFS - Credit | U26: Nice to have (20, not 80)
B27: Third party provider assumed | C27: L4 | D27: 1.1.3.2 | E27: Credit Assessment | F27: Assess customer creditworthiness using payment history, trade references, credit bureau data, financial statements and existing exposure to determine customer risk profile and recommended credit treatment | G27: Process | H27: N | Q27: GFS - Credit | R27: GFS - Credit | U27: Nice to have (20, not 80)
B28: Credit Platform | C28: L4 | D28: 1.1.3.3 | E28: Risk Scoring | F28: Apply approved scoring models, risk rules and credit policies to generate standardised customer credit risk rating and recommended credit controls | G28: Process | H28: Partial | Q28: GFS - Credit | R28: GFS - Credit | U28: Nice to have (20, not 80)
B29: Credit Platform | C29: L4 | D29: 1.1.3.4 | E29: Credit Decisioning | F29: Determine credit outcome based on risk assessment and policy thresholds (e.g., approve, approve with restrictions, apply credit hold, escalate for review or reject) and define provisional payment terms where applicable | G29: Process | H29: Partial | Q29: GFS - Credit | R29: GFS - Credit | U29: Nice to have (20, not 80)
B30: Credit Platform | C30: L4 | D30: 1.1.3.5 | E30: Credit Limit Assignment | F30: Establish formal customer credit limits for key accounts based on approved credit risk profile, forecasted exposure and available customer financial or credit information | G30: Process | H30: Partial | Q30: GFS - Credit | R30: GFS - Credit
B31: ERP | C31: L4 | D31: 1.1.3.6 | E31: ERP Credit Master Update | F31: Update ERP customer credit master data including approved credit status, formal credit limit, payment terms, risk rating, credit limits and hold indicators | G31: Process | H31: Y | Q31: Automated (or GFS - Credit in absence of automation) | R31: GFS - Credit | U31: Nice to have (20, not 80)
B32: Credit Platform | C32: L4 | D32: 1.1.3.7 | E32: Notify Stakeholders | F32: Notify relevant stakeholders of approved credit status, payment terms, credit restrictions or hold conditions | G32: Process | H32: Y | Q32: Automated (or GFS - Credit in absence of automation) | R32: GFS - Credit | U32: Nice to have (20, not 80)
B33: ERP | C33: L4 | D33: 1.1.3.8 | E33: Periodic Credit Review Cycle Setup | F33: Establish periodic credit review requirements and ongoing monitoring controls for key accounts. Define review frequency and escalation thresholds based on customer credit risk profile, forecasted exposure and ongoing payment performance where applicable | G33: Process | H33: Partial | Q33: GFS - Credit | R33: GFS - Credit
B34: CRM | C34: L3 | D34: 1.1.4 | E34: Multi-Division Engagement Setup | F34: Determine whether customer engagement requires a multi-division operating model (including CIC-contracted customers) and establish parent division ownership, commercial alignment and billing structure prior to contract execution | G34: Process | H34: N | Q34: Commercial Affairs | R34: Sales | S34: Client Services / Account Managers
B35: N/A | C35: L4 | D35: 1.1.4.1 | E35: Multi-Division Engagement Structure Required (including IHL)? | F35: Determine whether multiple divisions are participating in delivery, contracting or billing under a shared client relationship, MSA framework or centralised billing structure | G35: ="Decision If yes, proceed to step "&D36&" If no, proceed to "&D41&"" -> Decision If yes, proceed to step 1.1.4.2 If no, proceed to 1.1.5 | H35: N | Q35: Commercial Affairs | R35: Sales | S35: Client Services / Account Managers
B36: CRM | C36: L4 | D36: 1.1.4.2 | E36: Parent Division Assignment | F36: Assign parent division for the engagement / customer account based on agreed ownership criteria. Point of Origination drives parent assignment for new customers. For existing customers, determine parent ownership based on agreed commercial and delivery factors (e.g., revenue share, delivery footprint, key account ownership). Record agreed parent division ownership within CRM / account structure where applicable | G36: Process | H36: N | Q36: Commercial Affairs | R36: Sales | S36: Client Services / Account Managers
B37: N/A | C37: L4 | D37: 1.1.4.3 | E37: Participating Division Identification | F37: Identify divisions participating in delivery, billing or commercial ownership for the engagement | G37: Process | H37: N | Q37: Commercial Affairs | R37: Sales | S37: Client Services / Account Managers
B38: N/A | C38: L4 | D38: 1.1.4.4 | E38: Common Pricing & Commercial Structure Alignment | F38: Define common pricing structures, rate cards and shared commercial terms across participating divisions. Where agreement cannot be reached, parent division retains final commercial decision authority | G38: Process | H38: N | Q38: Commercial Affairs | R38: Sales | S38: Client Services / Account Managers
B39: N/A | C39: L4 | D39: 1.1.4.5 | E39: Division Scope & Billing Allocation | F39: Define division-level delivery scope, billing responsibility and billing-on-behalf structure aligned to parent division requirements | G39: Process | H39: N | Q39: Commercial Affairs | R39: Sales | S39: Client Services / Account Managers
B40: N/A | C40: L4 | D40: 1.1.4.6 | E40: Parent Division Change Control | F40: As required, manage controlled reassignment of parent division ownership based on material changes in revenue share, delivery footprint or strategic account ownership | G40: Process | H40: N | Q40: Commercial Affairs | R40: Sales | S40: Client Services / Account Managers
B41: CLM / Contract Capture Agent | C41: L3 | D41: 1.1.5 | E41: Master Services Agreement (MSA) management | F41: Establish or validate the governing Master Services Agreement (MSA), define high-level commercial and billing framework terms, complete legal execution and capture contractual data required to support downstream project setup, billing and revenue recognition processes | G41: Process | H41: Partial | I41: No CLM. MSAs stored in HighQ; SOWs in Maconomy per project. Larger clients propose their own contract templates. No e-signature integration. Contract routing is manual. | J41: No CLM tool. Contracts stored across multiple repositories (HubSpot, Certinia, HighQ). Identifying the correct MSA/SOW combination relies on team knowledge. No DocuSign - manual signature process. | K41: No CLM. MSAs stored as PDFs on local network drives per country in local languages. No standard process - managed locally. No e-signature. | L41: No CLM tool. MSAs created in Teams drives from client briefs. Scope templates are client-specific. No e-signature. Pricing negotiated via email. | M41: Client Services / Legal | N41: Client Services (Account Managers) | O41: Client Services / Project Operations | P41: Client Services | Q41: Commercial Affairs | R41: Sales | V41: MM: Correction to Column I: SOW's stored by Project (not by client)
B42: CLM | C42: L4 | D42: 1.1.5.1 | E42: Existing MSA Check | F42: Determine whether a valid MSA already exists for the customer or parent/affiliate group | G42: ="Decision If yes, proceed to step "&D50&" If no, proceed to "&D43&"" -> Decision If yes, proceed to step 1.1.5.9 If no, proceed to 1.1.5.2 | H42: N | M42: Client Services | N42: Client Services (Account Managers) | O42: Client Services | P42: Client Services | Q42: Commercial Affairs | R42: Sales
B43: CLM | C43: L4 | D43: 1.1.5.2 | E43: Select MSA Template | F43: Select appropriate MSA template based on division, service line and legal jurisdiction | G43: Process | H43: N | M43: Client Services / Legal | N43: Client Services (Account Managers) | O43: Client Services / Project Operations | P43: Client Services | Q43: Commercial Affairs | R43: Sales
B44: CLM | C44: L4 | D44: 1.1.5.3 | E44: Populate MSA Master Data & Reference ID | F44: Populate customer, legal and billing master data within MSA template. Generate MSA reference identifier within CLM for downstream project setup and invoicing processes. Where applicable, align MSA master data to agreed parent division ownership and billing structure, and capture participating divisions/entities | G44: Process | H44: N | Q44: Commercial Affairs | R44: Sales | S44: Client Services / Account Managers | AC44: MSA reference ID
B45: CLM | C45: L4 | D45: 1.1.5.4 | E45: Customer Affiliate Entity Identification | F45: Identify customer affiliate entities, subsidiaries or related billing entities that may engage under the MSA or future SOWs and determine applicability to the contractual and billing structure | G45: Process | H45: N | Q45: Commercial Affairs | R45: Sales | S45: Client Services / Account Managers
B46: CLM | C46: L4 | D46: 1.1.5.5 | E46: Country-Specific e-Invoicing Rule Validation | F46: Validate whether local e-invoicing regulations apply based on billing jurisdiction, billing entity and customer requirements. If required, capture e-invoicing identifiers where applicable | G46: Process | H46: N | Q46: Commercial Affairs | R46: Sales | S46: Client Services / Account Managers | AC46: E-invoicing (+ generating invoice out of ERP)
B47: CLM | C47: L4 | D47: 1.1.5.6 | E47: Populate High-level Commercial Terms | F47: Define high-level contractual and billing framework terms including payment terms, currency, billing frequency, delivery format (e.g., e-invoicing), rate cards (if applicable) and agreed discount / rebate structure. . Where applicable, align commercial terms to agreed parent division structure and permit use of scheduled billing arrangements to support downstream billing operations and invoice automation | G47: Process | H47: N | M47: Client Services | N47: Client Services (Account Managers) | O47: Client Services | P47: Client Services | Q47: Commercial Affairs | R47: Sales | S47: Client Services / Account Managers
B48: CLM | C48: L4 | D48: 1.1.5.7 | E48: Legal Review | F48: Use CLM workflow to route draft MSA to Legal for review of draft MSA terms, including non-standard clauses, commercial deviations and customer-specific contractual requirements prior to execution | G48: Process | H48: Partial | Q48: Legal | R48: Legal | S48: Commercial Affairs / Client Services / Account Managers
B49: CLM | C49: L4 | D49: 1.1.5.8 | E49: Legal Approval? | F49: Determine whether Legal approves the MSA draft for customer execution. If rejected, return with comments | G49: ="Decision If yes, proceed to step "&D50&" If no, proceed to "&D43&"" -> Decision If yes, proceed to step 1.1.5.9 If no, proceed to 1.1.5.2 | H49: N | Q49: Legal | R49: Legal
A50: X | B50: Contract Capture Agent | C50: L4 | D50: 1.1.5.9 | E50: Draft MSA Upload to Agent | F50: Upload Legal-approved, unsigned MSA document to Contract Capture Agent (via HighQ integration or direct upload) to establish version control prior to execution routing Key MSA components are extracted (e.g., MSA reference ID) and structured (e.g., key customer, commercial and contractual data) to support project setup. Links to parent MSA, if applicable | G50: Process | H50: Partial | I50: No contract capture agent. Contracts stored in HighQ (MSAs) and Maconomy (SOWs) separately. | J50: No contract capture agent or tool. SOW/pricing documents manually uploaded to multiple repositories. | K50: No contract capture agent. Contracts stored as PDFs on network drives. | L50: No contract capture agent. Contracts on Teams drives with no structured data extraction. | Q50: Commercial Affairs | R50: Sales
B51: CLM (DocuSign) | C51: L4 | D51: 1.1.5.10 | E51: Internal Signature Routing | F51: Where possible be the first to sign within HighQ via DocuSign integration (enables technology selection). Copy relevant stakeholders for automated notification upon executed signature | G51: Process | H51: Partial | I51: MSAs and SOWs are executed via DocuSign, Adobe Sign, etc., with signature requests initiated either by the client or by Evoke. | J51: No DocuSign. Contracts sent manually (email). Manual signature process. | K51: No DocuSign. Contracts in local languages sent manually per country. Regulations vary significantly by country. | L51: No DocuSign. Contracts sent and negotiated manually via email. | M51: Client Services | N51: Client Services (Account Managers) | O51: Client Services | P51: Client Services | Q51: Commercial Affairs | R51: Sales | S51: Client Services / Account Managers | V51: KV: MSAs and SOWs are executed via DocuSign, Adobe Sign, etc., with signature requests initiated either by the client or by Evoke. | AC51: Starting principle is that Inizio (CA team) signs first - to inform technology, who's across it in CC for routing and version control (with right payment terms)
B52: CLM (DocuSign) | C52: L4 | D52: 1.1.5.11 | E52: Send Contract to Client | F52: Transmit internally approved MSA to customer signatories through DocuSign execution workflow | G52: Process | H52: Partial | I52: MSAs and SOWs are executed via DocuSign, Adobe Sign, etc., with signature requests initiated either by the client or by Evoke. | J52: No DocuSign. Contracts sent manually (email). Manual signature process. | K52: No DocuSign. Contracts in local languages sent manually per country. Regulations vary significantly by country. | L52: No DocuSign. Contracts sent and negotiated manually via email. | M52: Client Services | N52: Client Services (Account Managers) | O52: Client Services | P52: Client Services | Q52: Commercial Affairs | R52: Sales
B53: CLM (DocuSign) | C53: L4 | D53: 1.1.5.12 | E53: Client Reviews & Signs Contract | F53: Client reviews, negotiates (where applicable) and executes e-signature within HighQ (via DocuSign integration). Executed version replaces unsigned draft within CLM. Agent captures executed signature | G53: Process | H53: Partial | M53: Client Services | N53: Client Services (Account Managers) | O53: Client Services | P53: Client Services | Q53: Client (external) | R53: Sales
B54: CLM (DocuSign) | C54: L4 | D54: 1.1.5.13 | E54: Exception: Customer Signs First? | F54: ="Determine whether the customer executed the MSA prior to completion of internal signature-first process (at step "&D51&")" -> Determine whether the customer executed the MSA prior to completion of internal signature-first process (at step 1.1.5.10) | G54: ="Decision If yes, proceed to step "&D55&" If no, proceed to "&D57&"" -> Decision If yes, proceed to step 1.1.5.14 If no, proceed to 1.1.5.16 | H54: Partial | Q54: Client (external) | R54: Sales
A55: X | B55: Contract Capture Agent | C55: L4 | D55: 1.1.5.14 | E55: Upload Customer-Signed MSA to Agent | F55: Upload customer-signed MSA draft to Contract Capture Agent (via email or direct upload) for review of iteration history and contractual changes prior to internal execution completion. If changes were made to Legal-approved version, route back to Legal for review. Previous MSA versions are appended for version control | G55: Process | H55: Partial | Q55: Commercial Affairs | R55: Sales
A56: X | B56: Contract Capture Agent / CLM (DocuSign) | C56: L4 | D56: 1.1.5.15 | E56: Internal Signature Completion | F56: Route Legal-approved, customer-signed MSA for internal execution completion following Agent review of iteration history and contractual changes | G56: Process | H56: Partial | Q56: Commercial Affairs | R56: Sales
A57: X | B57: Contract Capture Agent | C57: L4 | D57: 1.1.5.16 | E57: Contract Execution Validation | F57: Confirms counterparty signatures are captured and the contract is legally binding before proceeding. Change document status to "Executed" | G57: Process | H57: Y | M57: Client Services / Legal | N57: Client Services (Account Managers) | O57: Client Services | P57: Client Services | Q57: AI Agent - Contract Capture (or Commercial Affairs in absence of Agent) | R57: Sales
A58: X | B58: Contract Capture Agent / CLM | C58: L4 | D58: 1.1.5.17 | E58: Push Executed MSA to HighQ | F58: Push fully executed MSA and associated execution metadata to HighQ CLM as the contractual system of record | G58: Process | H58: Y | Q58: AI Agent - Contract Capture (or Commercial Affairs in absence of Agent) | R58: Sales
B59: ERP | C59: L4 | D59: 1.1.5.18 | E59: Customer Affiliate Master Data Setup Request | F59: ="Initiate creation or update of customer master data records for identified client affiliate entities (at step "&D45&") required to support downstream contracting, billing, invoicing and reporting processes" -> Initiate creation or update of customer master data records for identified client affiliate entities (at step 1.1.5.4) required to support downstream contracting, billing, invoicing and reporting processes | G59: Process | H59: N | Q59: Client Services / Account Managers | R59: Client Services / Account Managers
A60: X | B60: Contract Capture Agent | C60: L4 | D60: 1.1.5.19 | E60: Notification to GFS | F60: Automated notification sent to GFS to prompt for client portal setup and e-invoicing configuration, if applicable | G60: Process | H60: Y | M60: Client Services / Legal | N60: Client Services (Account Managers) | O60: Client Services | P60: Client Services | Q60: AI Agent - Contract Capture (or Commercial Affairs in absence of Agent) | R60: Sales | AC60: Upstream notification to GFS
B61: Email | C61: L4 | D61: 1.1.5.20 | E61: Client Vendor Setup Initiation | F61: Prompt customer to onboard the organisation and participating entities as approved vendors within customer procurement, AP or invoicing systems to support downstream invoice submission and prevent billing bottlenecks | G61: Process | H61: N | Q61: GFS | R61: Client Services / Account Managers
B62: ERP | C62: L4 | D62: 1.1.5.21 | E62: Set Up Client Portal & E-Invoicing Billing Configuration | F62: Configure client portal access, e-invoicing and customer-specific invoice delivery requirements to support downstream billing process | G62: Process | H62: N | M62: Operations | N62: Project Operations | O62: Operations | P62: Project Operations | Q62: GFS | R62: Client Services / Account Managers | U62: ADD: Notification to GFS at Contracting stage [1.1.4.10] | AC62: Upstream notification to GFS
B63: CLM | C63: L2 | D63: 1.2 | E63: SOW, Order Entry & Validation (incl. POs) | F63: Execute Statement of Work (SOW) incl. scope, deliverables, and pricing. Set up the contract/order in the ERP system and prepare for project setup | G63: Process | H63: Partial | I63: Entirely manual SOW process. No automated validation. For large clients, portals (e.g., DecideWare) require manual entry of 100s of rows per SOW, sometimes monthly. No standard rate card repository. | J63: Dual-system flow: HubSpot to Certinia. SOW/pricing manually uploaded to multiple places. POs arrive via Ariva portal, email, or direct contact - no unified intake. Account manager manages POs; GFS inputs into Certinia. | K63: SOW sent via email to contact team for Oracle BPM setup. Individual pricing models per client. EU: Project managers provide Excel to Finance for PPM data entry. All rates managed outside PPM in Excel. | L63: All manual - access to SOW/MSA is limited. Contract is a system term (not PDF) in Oracle. Budget changes don't auto-update contract funding. Every project change requires manual contract update, often multiple times per month. | M63: Ops. / Div. Finance | N63: Operations | O63: Ops / Div. Finance | P63: Operations | Q63: Client Services / Account Managers | R63: Client Services / Account Managers | S63: Commercial Affairs
B64: CLM | C64: L3 | D64: 1.2.1 | E64: SOW initiation / amendment | F64: Receive new project opportunity | G64: Process | H64: N | M64: Client Services | N64: Operations | O64: Client Services (BD / Account Managers) | P64: Operations | Q64: Client Services / Account Managers | R64: Client Services / Account Managers | U64: OPEN: Medical - MSAs and Global Pos; no SOW)
B65: CLM | C65: L4 | D65: 1.2.1.1 | E65: Project Amendment? | F65: Determine whether scope is related to an existing project and requires amendment to the SOW | G65: ="Decision If yes, proceed to step "&D71&" If no, proceed to "&D66&"" -> Decision If yes, proceed to step 1.2.2.5 If no, proceed to 1.2.2 | H65: N | M65: Client Services | N65: Client Services (Account Managers) | O65: Client Services | P65: Client Services | Q65: Client Services / Account Managers | R65: Client Services / Account Managers | S65: Commercial Affairs
B66: CLM / Contract Capture Agent | C66: L3 | D66: 1.2.2 | E66: Draft SOW | F66: Develop scope, deliverables and timelines. Define pricing and commercial terms. Align resourcing and effort with delivery. Generate SOW document | G66: Process | H66: Partial | I66: 70% use SOW templates within client MSA; 30% use internal template. Larger clients propose their own. No CLM. Drafting is manual in Word/Excel. | J66: SOW templates exist in HubSpot/Certinia but differ by entity. Pricing frequently built in Excel before system entry. No standardised CLM-based drafting. | K66: Pricing model individual for every client, embedded in each SOW. No standardised template-based drafting. Contracts vary by country with different regulatory requirements. | L66: Scopes of work template-specific for clients based on briefs. Drafted in Word/Excel on Teams drives. Oracle creates new templates for new products/clients. | M66: Client Services | N66: Operations | O66: Client Services | P66: Operations | Q66: Client Services / Account Managers | R66: Client Services / Account Managers | S66: Commercial Affairs
B67: CLM | C67: L4 | D67: 1.2.2.1 | E67: Participating Division Identification | F67: Identify division(s) participating in delivery and billing for the proposed scope of work aligned to the previously agreed parent-child structure, if applicable | G67: Process | H67: N | Q67: Client Services / Account Managers | R67: Client Services / Account Managers | S67: Commercial Affairs
B68: CLM | C68: L4 | D68: 1.2.2.2 | E68: Select SOW Template (CLM) | F68: Select appropriate SOW template based on division, commercial model, project type and customer requirements. Ensure the selected template contains structured contractual, commercial, billing and revenue recognition elements required to support downstream automation | G68: Process | H68: N | M68: Client Services | N68: Client Services (Account Managers) | O68: Client Services | P68: Client Services | Q68: Client Services / Account Managers | R68: Client Services / Account Managers | S68: Commercial Affairs | U68: CONSIDER Client templates (Pfizer) | AC68: To the extent possible, utilize SOW structure templates (e.g., structured inputs). De minimus sections w/in SOW (project master data; billing data; e-invoicing reqs; commercial model; delivery milestones; etc.) Include MSA reference and SOW reference/Project Number
B69: CLM | C69: L4 | D69: 1.2.2.3 | E69: Populate Contractual Reference Data | F69: Populate contracting entities, participating divisions, customer references and applicable MSA reference information in line with agreed parent division structure. Include MSA reference and generate SOW reference ID | G69: Process | H69: N | Q69: Client Services / Account Managers | R69: Client Services / Account Managers | S69: Commercial Affairs
B70: CLM | C70: L4 | D70: 1.2.2.4 | E70: Customer Affiliate Entity Identification | F70: Identify customer affiliate entities, subsidiaries or related billing entities that may engage under the SOW | G70: Process | H70: N | Q70: Client Services / Account Managers | R70: Client Services / Account Managers | S70: Commercial Affairs
B71: CLM | C71: L4 | D71: 1.2.2.5 | E71: Define Scope & Delivery Approach | F71: Establish deliverables, timeline, milestones, dependencies, etc. Distinguish between agreed vs. optional scope | G71: Process | H71: N | I71: Deliverables and milestones vary across project types and brands CH: Need to work on a standarized scope and delivery approach. Deliverables and milestones vary across project types and brands. | M71: Client Services | N71: Operations | O71: Client Services / Project Operations | P71: Operations | Q71: Client Services / Account Managers | R71: Client Services / Account Managers | S71: Commercial Affairs | V71: CH: Need to work on a standarized scope and delivery approach. Deliverables and milestones vary across project types and brands. Noted - no update made
B72: CLM | C72: L4 | D72: 1.2.2.6 | E72: Define Commercial & Billing Structure | F72: Define engagement-specific commercial model, rates/fees, billing triggers and upfront payment requirements (if applicable) for the proposed scope of work. For multi-division engagements, establish consolidated billing and align commercial terms to the designated Parent division. Where permitted under agreed MSA terms, use scheduled billing arrangements for T&M and Fixed Fee engagements to simplify downstream billing and invoice generation. Define billable vs. non-billable guidelines | G72: Process | H72: N | I72: No standard rate card repository. Pricing defined manually per engagement although some fixed fee pricing done using standard deliverables rate card. KV: Somewhat evenly split between T&M and fixed fee/milestone | J72: Pricing models frequently built outside system in Excel then entered into HubSpot/Certinia. Vynamic ~98% fixed fee; Putnam ~99% fixed fee. | K72: Pricing model in every SOW, individual for every client. US: 20M consulting T&M; rest is fixed billing per day/month. EU: Daily rate per working day + passthrough costs. | L72: Pricing negotiated via email with client. Most projects are fixed fee. Rates are manually managed. | M72: Client Services / Div. Finance | N72: Operations | O72: Client Services / Div. Finance | P72: Operations | Q72: Client Services / Account Managers | R72: Client Services / Account Managers | S72: Commercial Affairs | V72: KV: Somewhat evenly split between T&M and fixed fee/milestone. Some fixed fee pricing done using standard deliverables rate card. Noted - no update made
B73: CLM | C73: L4 | D73: 1.2.2.7 | E73: Define Pass-Through Treatment | F73: Define pass-through treatment based on agreed commercial structure (e.g., percentage markup, fixed fee with or without markup, direct recharge, mgmt. / service fee), and related invoicing requirements (e.g., line item detail) | G73: Process | H73: N | I73: No standard rate card repository. Pricing defined manually per engagement although some fixed fee pricing done using standard deliverables rate card. KV: Somewhat evenly split between T&M and fixed fee/milestone | J73: Pricing models frequently built outside system in Excel then entered into HubSpot/Certinia. Vynamic ~98% fixed fee; Putnam ~99% fixed fee. | K73: Pricing model in every SOW, individual for every client. US: 20M consulting T&M; rest is fixed billing per day/month. EU: Daily rate per working day + passthrough costs. | L73: Pricing negotiated via email with client. Most projects are fixed fee. Rates are manually managed. | M73: Client Services / Div. Finance | N73: Operations | O73: Client Services / Div. Finance | P73: Operations | Q73: Client Services / Account Managers | R73: Client Services / Account Managers | S73: Commercial Affairs
B74: CLM | C74: L4 | D74: 1.2.2.8 | E74: Define Resourcing & Effort | F74: Define resourcing and effort requirements to support delivery | G74: Process | H74: N | I74: CH: Inconsistent approach given the various types of businesses brought on | M74: Client Services / Operations (Resource Mgmt) | N74: Operations | O74: Client Services / Project Operations | P74: Operations | Q74: Client Services / Account Managers | R74: Client Services / Account Managers | S74: Staffing | V74: CH: Inconsistent approach given the various types of businesses we have brought on. Noted - no update made
B75: CLM | C75: L4 | D75: 1.2.2.9 | E75: Draft SOW Document | F75: Generate draft SOW document using structured contractual, commercial and billing inputs | G75: Process | H75: N | M75: Client Services | N75: Operations | O75: Client Services | P75: Operations | Q75: Client Services / Account Managers | R75: Client Services / Account Managers | S75: Commercial Affairs
B76: CLM | C76: L4 | D76: 1.2.2.10 | E76: Scope Change? | F76: Determine whether there is a scope change after initial SOW draft | G76: ="Decision If yes, proceed to step "&D77&" If no, proceed to "&D79&"" -> Decision If yes, proceed to step 1.2.2.11 If no, proceed to 1.2.2.13 | H76: N | I76: CH: Scope changes are common month to month. | M76: Client Services | N76: Client Services (Account Managers) | O76: Client Services | P76: Client Services | Q76: Client Services / Account Managers | R76: Client Services / Account Managers | S76: Commercial Affairs | V76: CH: Scope changes are common month to month. Noted - no update made
B77: CLM | C77: L4 | D77: 1.2.2.11 | E77: Redraft SOW Document or Document Changes via Structured Letter | F77: Update draft SOW or document agreed scope, pricing or commercial changes prior to downstream review and approval. Alternatively, capture authorised scope changes in letter or email from client (using structured inputs) with MSA / SOW reference included | G77: Process | H77: N | I77: CH: Current process is done through client calls and reconciliation meetings for scope changes | M77: Client Services | N77: Client Services (Account Managers) | O77: Client Services | P77: Client Services | Q77: Client Services / Account Managers | R77: Client Services / Account Managers | S77: Commercial Affairs | V77: CH: Current process is done through client calls and recon meetings for scope changes. Noted - no update made | AC77: MSA number; SOW reference number; scope changes captured via structured template (either in amended SOW or letter format)
B78: CLM (DocuSign) | C78: L4 | D78: 1.2.2.12 | E78: Internal Signature Routing | F78: Where possible be the first to sign within HighQ via DocuSign integration (enables technology selection). Copy relevant stakeholders for automated notification upon executed signature | G78: Process | H78: Partial | Q78: Client Services / Account Managers | R78: Client Services / Account Managers | S78: Commercial Affairs
A79: X | B79: Contract Capture Agent | C79: L4 | D79: 1.2.2.13 | E79: Draft SOW Upload to Agent | F79: Upload draft SOW document (or authorised amendment letter) to Contract Capture Agent via email or direct upload for contractual review, data extraction and version control prior to execution routing Extract and structure key scope, pricing and billing data from the SOW to support project setup, revenue recognition and invoicing. Flag whether document is New or Amended. Link to parent SOW, if applicable, and governing MSA via MSA reference ID | G79: Process | H79: Partial | M79: Client Services / Legal | N79: Client Services (Account Managers) | O79: Client Services | P79: Client Services | Q79: Client Services / Account Managers | R79: Client Services / Account Managers
A80: X | B80: Contract Capture Agent | C80: L4 | D80: 1.2.2.14 | E80: Draft SOW Alignment to MSA? | F80: Review draft SOW against governing MSA to confirm alignment to agreed commercial, billing and contractual terms (e.g., payment terms). Link to governing MSA using reference ID | G80: Process | H80: Y | M80: Client Services / Legal | N80: Client Services (Account Managers) | O80: Client Services | P80: Client Services | Q80: AI Agent - Contract Capture (or Client Services/Acct Mgrs in absence of Agent) | R80: Client Services / Account Managers | S80: Commercial Affairs | AC80: Agent automatic check against MSA. Link all documents with Project Number and SOW/MSA reference
A81: X | B81: Contract Capture Agent | C81: L4 | D81: 1.2.2.15 | E81: SOW Alignment Discrepancy Resolution | F81: Identify and resolve discrepancies. Update and reupload draft SOW where required | G81: Process | H81: N | M81: Client Services / Legal | N81: Client Services (Account Managers) | O81: Client Services | P81: Client Services | Q81: Client Services / Account Managers | R81: Client Services / Account Managers | S81: Commercial Affairs
A82: X | B82: Contract Capture Agent / PSA / PowerBI | C82: L3 | D82: 1.2.3 | E82: At-Risk Project Activation on Draft SOW | F82: Exception process allowing project activation and commencement of work prior to full SOW execution using approved draft contractual documentation and documented customer authorisation. Apply time-bound controls, risk approvals and escalation requirements until contractual execution is complete. Use 'Proposal' status in PSA to prevent revenue recognition until SOW is executed | G82: Process | H82: Partial | Q82: Client Services / Account Managers | R82: Division Finance
A83: X | B83: Contract Capture Agent | C83: L4 | D83: 1.2.3.1 | E83: At-Risk Start Needed? | F83: Determine whether there is a business need to commence work prior to full SOW execution. Route the at-risk start request for internal approval. | G83: ="Decision If yes, proceed to step "&D84&" If no, proceed to "&#REF!&"" -> #REF! | H83: N | Q83: Client Services / Account Managers | R83: Client Services / Account Managers
A84: X | B84: Contract Capture Agent | C84: L4 | D84: 1.2.3.2 | E84: At-Risk Approval & Risk Acceptance | F84: Define working-at-risk time bounds and escalation requirements for unresolved client approvals or contract execution delays. Approval confirms acceptance of commercial and contractual risk | G84: Process | H84: N | Q84: Division Finance | R84: Division Finance | S84: Client Services / Account Managers | AC84: Some areas (e.g., Creative) don't have a defined process for getting approval to work at-risk while SOW is being completed. Added TIME BOUNDS for working at-risk
B85: PSA | C85: L4 | D85: 1.2.3.3 | E85: Proceed to Project Setup | F85: ="Click 'Submit' to proceed to project setup with unsigned SOW at "&D119&" using 'Proposal' status in PSA" -> Click 'Submit' to proceed to project setup with unsigned SOW at 1.3.1 using 'Proposal' status in PSA | G85: Process | H85: N | Q85: Client Services / Account Managers | R85: Client Services / Account Managers
B86: PowerBI Dashboard | C86: L4 | D86: 1.2.3.4 | E86: At-Risk Monitoring | F86: Monitor projects operating under at-risk ('Proposal') status and track incurred costs, aging and contractual execution status. If contract execution delay exceeds defined threshold (e.g., 2 weeks without executed SOW), trigger escalation to reassess continuation of work | G86: Process | H86: Partial | Q86: Client Services / Account Managers | R86: Division Finance | AC86: Establishing defined timebounds for review and escalation of at-risk work
B87: CLM (DocuSign) | C87: L3 | D87: 1.2.4 | E87: SOW Review & Execution | F87: Review, negotiate and execute SOW. Capture executed contractual data required to support downstream project setup, billing and revenue recognition processes | G87: Process | H87: Partial | M87: Client Services | N87: Operations | O87: Client Services | P87: Operations | Q87: Client Services / Account Managers | R87: Client Services / Account Managers | S87: Commercial Affairs
B88: CLM (DocuSign) | C88: L4 | D88: 1.2.4.1 | E88: Send SOW to Customer | F88: Transmit final SOW to client signatories via e-signature link within HighQ (via DocuSign integration) | G88: Process | H88: Partial | M88: Client Services | N88: Client Services (Account Managers) | O88: Client Services | P88: Client Services | Q88: Client Services / Account Managers | R88: Client Services / Account Managers | S88: Commercial Affairs
B89: Email / CLM | C89: L4 | D89: 1.2.4.2 | E89: Client Amendments | F89: Determine whether customer has proposed amendments, redlines or contractual changes to the SOW requiring internal review or update | G89: Process | H89: N | M89: Client Services / Legal | N89: Client Services (Account Managers) | O89: Client Services | P89: Client Services | Q89: Client Services / Account Managers | R89: Client Services / Account Managers | S89: Commercial Affairs
B90: CLM (DocuSign) | C90: L4 | D90: 1.2.4.3 | E90: Client Reviews & Signs SOW | F90: Customer reviews, negotiates (where applicable) and executes e-signature within HighQ via DocuSign integration. Executed version replaces unsigned draft within HighQ CLM. Agent captures executed signature | G90: Process | H90: Partial | M90: Client Services | N90: Client Services (Account Managers) | O90: Client Services | P90: Client Services | Q90: Client Services / Account Managers | R90: Client Services / Account Managers | S90: Commercial Affairs | V90: KM: Column F:SOW's are not stored in Hubspot
B91: CLM (DocuSign) | C91: L4 | D91: 1.2.4.4 | E91: Exception: Customer Signs First? | F91: ="Determine whether customer executed the SOW prior to completion of internal signature-first process (at step "&D78&")" -> Determine whether customer executed the SOW prior to completion of internal signature-first process (at step 1.2.2.12) | G91: ="Decision If yes, proceed to step "&D92&" If no, proceed to "&D94&"" -> Decision If yes, proceed to step 1.2.4.5 If no, proceed to 1.2.4.7 | H91: Partial | Q91: Client Services / Account Managers | R91: Client Services / Account Managers | S91: Commercial Affairs
A92: X | B92: Contract Capture Agent | C92: L4 | D92: 1.2.4.5 | E92: Upload Customer-Signed SOW to Agent | F92: Submit customer-signed SOW draft to Contract Capture Agent (via email or direct upload) for review of iteration history and contractual changes prior to internal execution completion. If changes were made to internal-approved version, route back to approver for review. Previous SOW versions are appended for version control | G92: Process | H92: Partial | Q92: Client Services / Account Managers | R92: Client Services / Account Managers | S92: Commercial Affairs
B93: Contract Capture Agent / CLM (DocuSign) | C93: L4 | D93: 1.2.4.6 | E93: Internal Signature Completion | F93: Route customer-signed SOW for internal execution completion following Agent review of iteration history and contractual changes | G93: Process | H93: Partial | Q93: Client Services / Account Managers | R93: Client Services / Account Managers | S93: Commercial Affairs
A94: X | B94: Contract Capture Agent | C94: L4 | D94: 1.2.4.7 | E94: Contract Execution Validation | F94: Confirm that all counterparty signatures are captured and the contract is legally binding before proceeding. Change document status to "Executed" | G94: Process | H94: Y | M94: Client Services | N94: Client Services (Account Managers) | O94: Client Services | P94: Client Services | Q94: AI Agent - Contract Capture (or Client Services/Acct Mgrs in absence of Agent) | R94: Division Finance | S94: Commercial Affairs
A95: X | B95: Contract Capture Agent | C95: L4 | D95: 1.2.4.8 | E95: SOW Alignment to MSA? | F95: Re-review executed SOW against governing MSA to confirm alignment to agreed commercial, billing and contractual terms (e.g., payment terms). Link to governing MSA using reference ID | G95: ="Decision If yes, proceed to step "&D97&" If no, proceed to "&D96&"" -> Decision If yes, proceed to step 1.2.4.10 If no, proceed to 1.2.4.9 | H95: Y | M95: Client Services / Legal | N95: Client Services (Account Managers) | O95: Client Services | P95: Client Services | Q95: AI Agent - Contract Capture (or Client Services/Acct Mgrs in absence of Agent) | R95: Client Services / Account Managers | S95: Commercial Affairs | V95: MM: This step should be done before an SOW is sent to a cleint. [Updated - this is now secondary matching. See 1.2.2.10]
A96: X | B96: Contract Capture Agent | C96: L4 | D96: 1.2.4.9 | E96: SOW Alignment Discrepancy Resolution | F96: Identify and resolve discrepancies. Where discrepancies relate to participating child divisions, the parent division lead may delegate resolution activities to the applicable child division while retaining overall accountability for alignment and resolution completion Update SOW document (and route for re-approval) where required | G96: Process | H96: N | M96: Client Services / Legal | N96: Client Services (Account Managers) | O96: Client Services | P96: Client Services | Q96: Client Services / Account Managers | R96: Client Services / Account Managers | S96: Commercial Affairs
A97: X | B97: Contract Capture Agent | C97: L4 | D97: 1.2.4.10 | E97: Finance Approval Threshold Met? | F97: Determine whether executed SOW value exceeds defined approval threshold requiring Finance review prior to project activation | G97: ="Decision If yes, proceed to step "&D98&" If no, proceed to "&D99&"" -> Decision If yes, proceed to step 1.2.4.11 If no, proceed to 1.2.4.12 | H97: Y | Q97: AI Agent - Contract Capture (or Client Services/Acct Mgrs in absence of Agent) | R97: Client Services / Account Managers | S97: Commercial Affairs
A98: X | B98: Contract Capture Agent | C98: L4 | D98: 1.2.4.11 | E98: Finance Review & Approval | F98: Route executed SOW to Finance for review and approval where approval threshold is exceeded. Trigger automated notification to Finance and capture approval outcome prior to project activation | G98: Process | H98: Partial | Q98: Division Finance | R98: Division Finance | S98: Client Services / Account Managers
A99: Future Opportunity | B99: PSA | C99: L4 | D99: 1.2.4.12 | E99: Project Activation Trigger in PSA | F99: ="Push approved and executed SOW to PSA and activate project with “Active” status (or update existing project if this is an amendment to an existing project scope). See step "&D118&" for project activation steps" -> Push approved and executed SOW to PSA and activate project with “Active” status (or update existing project if this is an amendment to an existing project scope). See step 1.3 for project activation steps | G99: Process | H99: Y | Q99: AI Agent - Contract Capture (or Client Services/Acct Mgrs in absence of Agent) | R99: Client Services / Account Managers
A100: X | B100: Contract Capture Agent | C100: L4 | D100: 1.2.4.13 | E100: Push Executed SOW to HighQ | F100: Push fully executed SOW and associated execution metadata to HighQ CLM as the contractual system of record. Maintain linkage to governing MSA and executed contractual records | G100: Process | H100: Y | I100: Currently a manual step performed by Division Finance | J100: Currently a manual step performed by Division Finance | K100: Currently a manual step performed by Division Finance | L100: Currently a manual step performed by Division Finance | M100: Div. Finance | N100: Div. Finance | O100: Div. Finance | P100: Div. Finance | Q100: AI Agent - Contract Capture (or Client Services/Acct Mgrs in absence of Agent) | R100: Client Services / Account Managers | AC100: Move from Div Finance manual upload to automatic push to HighQ (or Commercial Affairs in absence of Agent)
B101: ERP | C101: L4 | D101: 1.2.4.14 | E101: Customer Affiliate Master Data Setup Request | F101: ="Initiate creation or update of customer master data records for identified client affiliate entities (at step "&D67&") required to support downstream contracting, billing, invoicing and reporting processes" -> Initiate creation or update of customer master data records for identified client affiliate entities (at step 1.2.2.1) required to support downstream contracting, billing, invoicing and reporting processes | G101: Process | H101: N | Q101: Client Services / Account Managers | R101: Client Services / Account Managers
...

Sheet Mapping
A1: Invoicing Process - GFS Steps
B4: Step | C4: As-is | D4: To-be | E4: Mapping | F4: Agent Considerations
B5: Issue Invoice
B6: P1 Create Invoice | C6: Create invoice | E6: ='Process Design'!D329 -> 5.3.2
B7: P1 Deliver Invoice | C7: Submit invoice to client | E7: ='Process Design'!D335 -> 5.3.3
B8: P2 Manual Integrations | C8: Invoicing team provides list of transactions that are available for billing to non-Oracle entities (multiple STEM entities; eventually 1 in Putnam). Potentially due to local outsourcing requirements. This happens automatically for Certinia and Oracle entities through an interface | D8: Move to Oracle or establish automated integration. Invoice generated out of ERP (Oracle/Maconomy). In the interim state, no change to as-is process (GFS) | E8: N/A (via integration or transition to Oracle). Capture in system initiatives list | F8: Capture in system initiatives list
B9: Invoice Resolution
B10: P2 Project Invoice Status | C10: - Individual invoice status (draft, submitted, etc.) What's invoicing status of this project; how much have I billed - Not all projects are single project; not all POs are single project. Invoicing team investigates | D10: - Invoice status tracking and balance billed to-date captured in Agent - OPEN: Flush out complexities outside of 1:1 matching (e.g., multi-PO) | E10: ="- "&'Process Design'!D278&" - "&'Process Design'!D334&"" -> - 5.1.3.1 - 5.3.2.5 | F10: Invoicing agent - balance billed to-date vs. PO / group of Pos ERP to track invoice status
B11: P3 Issues / Corrections | C11: - Invoice rejection resolution (e.g., incorrect/missing information or didn't hit milestone) - Notification to Billing team via email or Customer Portal. Dawn's team do Portal checks 1 week after invoices are submitted before handing off to Collections - First line of defense for resolution is GFS, then to Divisional Finance to interface with Client Services | D11: - Notification to Billing team via email or Customer Portal (no change) - Dawn's team can continue to check Portal checks after invoice submission (no change) - First line of defense for resolution is GFS, then Client Services. Divisional Finance is removed from intermediary step | E11: =""&'Process Design'!D338&" Portal checks - not explicitly added " -> 5.3.3.3 Portal checks - not explicitly added
B12: Obtain Milestone Approval
B13: P2 Initiate Milestone Update Requests | C13: Proactive unbilled escalation to Operations (Account Managers) via emailed PowerBI report (downloaded and emailed) | D13: To-be - proactive prompting straight to stakeholder via Invoicing Agent | E13: ='Process Design'!D351 -> 5.3.6.2 | F13: Invoicing agent - prompt Project Manager / Client Services for unbilled on Milestones and T&M | G13: PoC discussions: Periodic revew vs. prompts
B14: P2 Targeted Partner Meetings | C14: - Secondary escalation to Operations (Account Managers and Senior Individuals) via meeting - If there's an update to the milestone, that's usually taken by the Invoicing team | D14: - No change - Change management; Client Services should update held/cancelled milestones timely (prompt via KPI tracking on report produced by Agent) | E14: ='Process Design'!D352 -> 5.3.6.3 | F14: Invoicing agent - as per above | G14: PoC discussions: Periodic revew vs. prompts
B15: P3 Request Budget Updates | C15: When PO comes in or something wasn't represented properly on the invoice - request to Operations to update budget/project in system | D15: To be captured via Contract Capture agent at PO submission | E15: ='Process Design'!D109 -> 1.2.5.5 | F15: Contract capture agent - prompt Client Services to make updates
B16: Milestone Lifecycle
B17: P2 Process Milestone Updates | C17: Any change in system for metadata (e.g., invoice something but PO was closed; pass through cost classified as part of fees; bill-to entity; etc.). Today done by Invoicing team | D17: To-be state would be done by GFS | E17: ='Process Design'!D338 -> 5.3.3.3 | F17: Invoicing agent - GFS to work through invoice rejections queue
B18: P3 Oracle Site Creation | C18: No master data record exists. Reach out to Master Data team to get a site created so they can bill against - E.g., Europe signs contract; PO for both US and EU; only one signs SOW | D18: To-be state at MSA (Master Data), SOW (contract setup - groups and affiliates) and PO (affiliate) steps - ensure all affiliate entities are in Master Data | E18: ="- "&'Process Design'!D59&" - "&'Process Design'!D101&" - "&'Process Design'!D111&"" -> - 1.1.5.18 - 1.2.4.14 - 1.2.5.7
B19: P3 Client Vendor Registration | C19: Affiliate legal entity/agency needs to be added to Client system as Vendor. Usually done at the time a PO is submitted (would indicate a mismatch between SOW and PO). Today this is done by Invoicing team - Prompt is an inbound (at contracting; various steps) | D19: - To-be state would be done by GFS; Client Services accountable - If no PO, GFS | E19: ="- "&'Process Design'!D61&" - "&'Process Design'!D102&" - "&'Process Design'!D109&"" -> - 1.1.5.20 - 1.2.4.15 - 1.2.5.5
B20: P3 PO Placement | C20: A PO is forwarded to Invoicing team; need to add to system and register for milestones | D20: To-be state - would link to MSA/SOW/PO/project via Contract Capture Agent | E20: ='Process Design'!D115 -> 1.2.6.3 | F20: Contract capture agent - PO routing and linkage
B21: P3 Milestone Cancellations | C21: Milestones cancelled; Invoicing having conversations with Client Services who will hold last invoice; budget is reduced or taken as a write off; sent to Project Operations to action/track | D21: Change management - Client Service / Project Manager to close out those milestones rather than going to Project Ops | E21: ='Process Design'!D199 -> 3.4.1
B22: Risk Management & Escalations
B23: P4 Full Inbox Management | C23: Catch-all invoicing inbox related to invoicing - new bank account; invoice rejections; clients request accrual estimate; PO submission; etc. | D23: To-be state - any queries would be sent to a central mailbox monitored by GFS. Invoice / PO submissions should be routed to Agent. Update workflow status in Agent or Oracle (e.g., invoice rejection status) | E23: Multiple ServiceNow to be captured via System Initiatives list | F23: Invoicing agent or Oracle invoicing module - enable workflow tracking | G23: - ServiceNow - platform for GFS Collections (billing & revenue not currently in this model) - Potential to use ServiceNow to route emails to track workflow (?) - OPEN (potential for IT initiatives list); GFS review service now and where relevant to pass through to agent
B24: P4 Past Due Milestone Management | C24: Escalations. Similar to Targeted Partner Meetings, but with Finance instead of Operations | D24: To-be - proactive prompting straight to stakeholder via Invoicing Agent | E24: ='Process Design'!D352 -> 5.3.6.3 | F24: Invoicing agent - prompt Division Finance for unbilled on Milestones and T&M
B25: P4 PARR (Projects At-Risk Register) (report) | C25: - Secondary escalations (at Grainne level - monthly review). Projects that are active and generating revenue that don't have a PO. Distributed widely - No commercial model to put controls in to prevent time from being incurred. | D25: No change | E25: ='Process Design'!D353 -> 5.3.6.4 | F25: Both agents - flag clients that do/don't require a PO
B26: P4 Paperless Pursuits (report) | C26: All active projects that may start this month but don't have paperwork. Trending towards PARR but not at-risk yet. Accured income management - aging accrued income on project which may be fully contracted without authorisation to invoice. Distributed widely | D26: No change | E26: ='Process Design'!D353 -> 5.3.6.4

Sheet Unbilled Monitoring - extract
E9: Step | F9: As-is | G9: To-be
E10: P2 Initiate Milestone Update Requests | F10: Proactive unbilled escalation to Operations (Account Managers) via emailed PowerBI report (downloaded and emailed) | G10: To-be - proactive prompting straight to stakeholder via Invoicing Agent
E11: P2 Targeted Partner Meetings | F11: - Secondary escalation to Operations (Account Managers and Senior Individuals) via meeting - If there's an update to the milestone, that's usually taken by the Invoicing team | G11: - No change - Change management; Client Services should update held/cancelled milestones timely (prompt via KPI tracking on report produced by Agent)
E12: P4 Past Due Milestone Management | F12: Escalations. Similar to Targeted Partner Meetings, but with Finance instead of Operations | G12: No change
E13: P4 PARR (Projects At-Risk Register) (report) | F13: - Secondary escalations (at Grainne level - monthly review). Projects that are active and generating revenue that don't have a PO. Distributed widely - No commercial model to put controls in to prevent time from being incurred. | G13: No change
E14: P4 Paperless Pursuits (report) | F14: All active projects that may start this month but don't have paperwork. Trending towards PARR but not at-risk yet. Accured income management - aging accrued income on project which may be fully contracted without authorisation to invoice. Distributed widely | G14: No change
